numpee/.__init__.py.un~
numpee/__init__.py
numpee-1.9.3.dist-info/METADATA
numpee-1.9.3.dist-info/WHEEL
numpee-1.9.3.dist-info/RECORD
