Metadata-Version: 1.2
Name: numpee
Version: 1.9.3
Summary: Because it's pronounced Num-Pie
Home-page: https://github.com/Carreau/numpee
License: UNKNOWN
Author: Matthias Bussonnier
Author-email: bussonniermatthias@gmail.com
Classifier: License :: OSI Approved :: MIT License
Requires-Dist: numpy
